vlac/__init__.py
vlac/vlac.py
vlac/vlac_model.py
vlac-0.1.2.5.dist-info/LICENSE
vlac-0.1.2.5.dist-info/METADATA
vlac-0.1.2.5.dist-info/WHEEL
vlac-0.1.2.5.dist-info/top_level.txt
vlac-0.1.2.5.dist-info/RECORD
