Metadata-Version: 2.1
Name: vlac
Version: 0.1.2.5
Summary: Tool for creating document features
Home-page: https://github.com/MaartenGr/VLAC
Author: Maarten Grootendorst
Author-email: maartengrootendorst@gmail.com
License: MIT
Platform: UNKNOWN
Requires-Dist: numpy
Requires-Dist: sklearn
